MANIFEST.in
setup.py
bin/oauth-proxy
oauth_proxy/__init__.py
oauth_proxy/oauth_proxy.py
oauth_proxy.egg-info/PKG-INFO
oauth_proxy.egg-info/SOURCES.txt
oauth_proxy.egg-info/dependency_links.txt
oauth_proxy.egg-info/requires.txt
oauth_proxy.egg-info/top_level.txt
twisted/plugins/proxy.py