Metadata-Version: 1.0
Name: oauth-proxy
Version: 1.0.5
Summary: OAuth HTTP proxy
Home-page: http://github.com/mojodna/oauth-proxy
Author: Seth Fitzsimmons
Author-email: seth@mojodna.net
License: BSD License
Keywords: oauth proxy twisted
Platform: UNKNOWN
Classifier: Development Status :: 5 - Production/Stable
Classifier: Topic :: Utilities
Classifier: Topic :: Internet :: Proxy Servers
Classifier: License :: OSI Approved :: BSD License
